[
    {
       "relation": [
          "delegate_permission/common.handle_all_urls"
       ],
       "target": {
          "namespace": "android_app",
          "package_name": "edu.virginia.digitaltrails",
          "sha256_cert_fingerprints": [
             "1C:22:11:52:A2:F2:0D:07:1F:04:EE:9C:C7:38:5B:76:94:76:35:F2:71:86:2F:40:73:22:42:62:9E:96:17:76"
          ]
       }
    },
    {
      "relation": [
         "delegate_permission/common.handle_all_urls"
      ],
      "target": {
         "namespace": "android_app",
         "package_name": "edu.virginia.digitaltrails",
         "sha256_cert_fingerprints": [
            "D3:81:F1:D2:20:47:3A:60:35:E9:80:19:4B:5E:9F:45:B8:70:D3:70:FD:78:96:1E:96:DD:0D:CC:C7:5D:79:64"
         ]
      }
   }
]
